sharelatex/__init__.py
sharelatex/__version__.py
sharelatex/cli.py
slagit-2.0.2.dist-info/LICENSE
slagit-2.0.2.dist-info/METADATA
slagit-2.0.2.dist-info/WHEEL
slagit-2.0.2.dist-info/entry_points.txt
slagit-2.0.2.dist-info/top_level.txt
slagit-2.0.2.dist-info/RECORD
